softdelete/__init__.py
softdelete/managers.py
softdelete/models.py
soft_delete-0.2.2.dist-info/LICENSE
soft_delete-0.2.2.dist-info/METADATA
soft_delete-0.2.2.dist-info/WHEEL
soft_delete-0.2.2.dist-info/top_level.txt
soft_delete-0.2.2.dist-info/RECORD
