Metadata-Version: 2.1
Name: soft-delete
Version: 0.2.2
Summary: Abstraction to logical/soft delete in django models
Home-page: https://www.collabo.com.br/
Author: Collabo Software Ltda
Author-email: thomas@collabo.com.br
License: MIT
Platform: UNKNOWN
Classifier: Development Status :: 4 - Beta
Classifier: Environment :: Web Environment
Classifier: Framework :: Django
Classifier: Intended Audience :: Developers
Classifier: License :: OSI Approved :: MIT License
Classifier: Operating System :: OS Independent
Classifier: Programming Language :: Python
Classifier: Programming Language :: Python :: 2
Classifier: Programming Language :: Python :: 3
Classifier: Topic :: Software Development :: Libraries :: Python Modules
Requires-Dist: coverage (==4.0.3)
Requires-Dist: Django (>=1.9)
